solverai/__init__.py
solverai/_base_client.py
solverai/_client.py
solverai/_compat.py
solverai/_constants.py
solverai/_exceptions.py
solverai/_files.py
solverai/_models.py
solverai/_qs.py
solverai/_resource.py
solverai/_response.py
solverai/_streaming.py
solverai/_types.py
solverai/_version.py
solverai/py.typed
solverai/_utils/__init__.py
solverai/_utils/_logs.py
solverai/_utils/_proxy.py
solverai/_utils/_reflection.py
solverai/_utils/_resources_proxy.py
solverai/_utils/_streams.py
solverai/_utils/_sync.py
solverai/_utils/_transform.py
solverai/_utils/_typing.py
solverai/_utils/_utils.py
solverai/lib/.keep
solverai/resources/__init__.py
solverai/resources/repos/__init__.py
solverai/resources/repos/repos.py
solverai/resources/repos/sessions/__init__.py
solverai/resources/repos/sessions/events.py
solverai/resources/repos/sessions/sessions.py
solverai/resources/repos/sessions/status.py
solverai/resources/repos/sessions/turns.py
solverai/types/__init__.py
solverai/types/repo_list_response.py
solverai/types/vcs_provider.py
solverai/types/repos/__init__.py
solverai/types/repos/session.py
solverai/types/repos/session_create_params.py
solverai/types/repos/session_get_patch_params.py
solverai/types/repos/session_get_patch_response.py
solverai/types/repos/session_list_params.py
solverai/types/repos/session_list_response.py
solverai/types/repos/session_request_change_localizations_params.py
solverai/types/repos/session_solve_params.py
solverai/types/repos/session_status.py
solverai/types/repos/session_visibility.py
solverai/types/repos/turn.py
solverai/types/repos/sessions/__init__.py
solverai/types/repos/sessions/event_get_patch_params.py
solverai/types/repos/sessions/event_get_patch_response.py
solverai/types/repos/sessions/status_stream_params.py
solverai/types/repos/sessions/status_stream_response.py
solverai/types/repos/sessions/trace_event.py
solverai/types/repos/sessions/turn_get_change_localizations_response.py
solverai/types/repos/sessions/turn_get_patch_response.py
solverai-0.1.0a5.dist-info/METADATA
solverai-0.1.0a5.dist-info/WHEEL
solverai-0.1.0a5.dist-info/licenses/LICENSE
solverai-0.1.0a5.dist-info/RECORD
